BenBotAsync/__init__.py
BenBotAsync-3.0.2.dist-info/METADATA
BenBotAsync-3.0.2.dist-info/WHEEL
BenBotAsync-3.0.2.dist-info/top_level.txt
BenBotAsync-3.0.2.dist-info/RECORD
