Metadata-Version: 2.1
Name: BenBotAsync
Version: 3.0.2
Summary: Asynchronous Python wrapper for BenBot API.
Home-page: https://github.com/xMistt/BenBot
Author: xMistt
Classifier: Programming Language :: Python :: 3
Classifier: License :: OSI Approved :: MIT License
Classifier: Operating System :: OS Independent
